{
  "manifest": {
    "publishingInformation": {
      "locales": {
        "en-US": {
          "summary": "Sample Short Description",
          "examplePhrases": [
            "Alexa open hello world",
            "hello",
            "help"
          ],
          "name": "test",
          "description": "Sample Full Description"
        }
      },
      "isAvailableWorldwide": true,
      "testingInstructions": "Sample Testing Instructions.",
      "category": "KNOWLEDGE_AND_TRIVIA",
      "distributionMode": "PRIVATE",
      "distributionCountries": []
    },
    "apis": {
      "custom": {
        "endpoint": {
          "uri": "arn:aws:lambda:eu-west-2:661272765443:function:LawrenceHueAppStack-LawrenceHueAppSkillFunction11A-1I6N1QLH6BUQ8"
        }
      }
    },
    "manifestVersion": "1.0"
  }
}